{"name":"Break Fast","tagline":"Craftbukkit plugin to break blocks in one hit with optional drop.","body":"# Break *Fast*\r\n\r\nCurrent version: v1.0.1\r\n\r\nAllows players to destroy blocks with one hit.\r\n\r\nWhen enabled, you can break blocks in one hit. No special items required. You also have the option of having the block dropped when breaking it. Default behavior is not dropping broken blocks.\r\n\r\n\r\nCommands\r\n--------\r\n\r\n#### /BreakFast\r\n- alias: /bf\r\n- description: enables/disables the Break Fast plugin for you.\r\n- permissions: breakfast.use\r\n- default: op\r\n\r\n#### /BreakFastDrop\r\n- alias: /bfd\r\n- description: enables/disables dropping of blocks destroyed using Break Fast\r\n- permissions: breakfast.use\r\n- default: op\r\n\r\nUsage\r\n--------\r\n\r\nUsing Break *Fast* couldn't be easier, just enable Break *Fast* plugin then break blocks normally using left click.\r\n\r\nUsage steps:\r\n- Enable Break *Fast* with /BreakFast ( or /bf)\r\n- Break blocks with left click. This will only take one hit now.\r\n- [optionally] Enable Break *Fast* Drop with /BreakFastDrop (or /bfd)\r\n- Enabling Break *Fast* Drop means when Break *Fast* is enabled, broken blocks will drop into the world normally. Great for strip mining\r\n\r\nConfiguration\r\n--------\r\n\r\nThere is no configuration necessary for this plugin.\r\n\r\nPermissions\r\n--------\r\n\r\nbreakfast.use\r\n- allows usage of /BreakFast and /BreakFastDrop commands\r\n- defaults to op\r\n\r\nKnown Issues\r\n--------\r\n\r\n:white_check_mark: No known issues!\r\n","google":"","note":"Don't delete this file! It's used internally to help with page regeneration."}